algo_battle/__init__.py
algo_battle/__main__.py
algo_battle/app/__init__.py
algo_battle/app/cli.py
algo_battle/app/pyside2_gui.py
algo_battle/domain/__init__.py
algo_battle/domain/algorithmus.py
algo_battle/domain/arena.py
algo_battle/domain/teilnehmer.py
algo_battle/domain/util.py
algo_battle/domain/wettkampf.py
algo_battle/util/__init__.py
algo_battle/util/builtin_algorithmen.py
algo_battle/util/input.py
algo_battle-0.1.1.post2.dist-info/LICENSE.txt
algo_battle-0.1.1.post2.dist-info/METADATA
algo_battle-0.1.1.post2.dist-info/WHEEL
algo_battle-0.1.1.post2.dist-info/top_level.txt
algo_battle-0.1.1.post2.dist-info/RECORD
