Metadata-Version: 2.1
Name: algo-battle
Version: 0.1.1.post2
Summary: Educational Project to let different algorithms compete against each other. Currently only available in German.
Home-page: UNKNOWN
Author: CoderDojo Karlsruhe, Lennart Hensler and Mark Weinreuter
Author-email: coderdojo.karlsruhe@gmail.com
License: UNKNOWN
Project-URL: Source, https://github.com/coderdojoka/algo-battle
Platform: UNKNOWN
Classifier: Development Status :: 4 - Beta
Classifier: Environment :: Console
Classifier: Environment :: X11 Applications :: Qt
Classifier: Intended Audience :: Education
Classifier: Intended Audience :: End Users/Desktop
Classifier: License :: OSI Approved :: MIT License
Classifier: Natural Language :: German
Classifier: Operating System :: OS Independent
Classifier: Programming Language :: Python :: 3.5
Classifier: Topic :: Education
Requires-Python: >=3.5
Requires-Dist: numpy (>=1.16.2)
Requires-Dist: pandas (>=0.24.2)
Requires-Dist: Pillow (>=5.4.1)
Requires-Dist: PySide2 (>=5.12.2)
